logmmse/__init__.py
logmmse/base.py
logmmse/logmmse.py
logmmse/utils.py
logmmse-1.5.dist-info/LICENSE
logmmse-1.5.dist-info/METADATA
logmmse-1.5.dist-info/WHEEL
logmmse-1.5.dist-info/top_level.txt
logmmse-1.5.dist-info/RECORD
