Metadata-Version: 2.1
Name: logmmse
Version: 1.5
Summary: A python implementation of the LogMMSE speech enhancement/noise reduction alogrithm
Home-page: https://github.com/wilsonchingg/logmmse
Author: Rajiv Poddar, Wilson Ching (Fork Author)
Author-email: wilsonchingg96@gmail.com
License: MIT
Platform: UNKNOWN
Requires-Dist: numpy
Requires-Dist: scipy
